nbmorph/__init__.py
nbmorph/box_kernel.py
nbmorph/diamond_kernel.py
nbmorph/minmax.py
nbmorph/mode.py
nbmorph/morphology.py
nbmorph/ops.py
nbmorph/utils.py
nbmorph/zero_edges.py
nbmorph-0.2.0.dist-info/licenses/LICENSE
nbmorph-0.2.0.dist-info/METADATA
nbmorph-0.2.0.dist-info/WHEEL
nbmorph-0.2.0.dist-info/top_level.txt
nbmorph-0.2.0.dist-info/RECORD
