Metadata-Version: 2.4
Name: nbmorph
Version: 0.2.0
Summary: A small package with Numba-accelerated morphological operations.
Author-email: Marius Causemann <mariusca@simula.no>
License: MIT License
Classifier: Programming Language :: Python :: 3
Classifier: License :: OSI Approved :: MIT License
Classifier: Operating System :: OS Independent
Classifier: Intended Audience :: Science/Research
Classifier: Topic :: Scientific/Engineering :: Image Processing
Requires-Python: >=3.8
License-File: LICENSE
Requires-Dist: numpy
Requires-Dist: numba
Provides-Extra: test
Requires-Dist: pytest; extra == "test"
Requires-Dist: pytest-cov; extra == "test"
Requires-Dist: fastmorph; extra == "test"
Dynamic: license-file
